memos_cmp/__init__.py
memos_cmp/server.py
memos_mcp-0.1.4.dist-info/METADATA
memos_mcp-0.1.4.dist-info/WHEEL
memos_mcp-0.1.4.dist-info/entry_points.txt
memos_mcp-0.1.4.dist-info/RECORD
