Metadata-Version: 2.4
Name: memos-mcp
Version: 0.1.4
Summary: Memos MCP服务器
Project-URL: Homepage, https://github.com/yuzhi-jiang/memos-mcp
Project-URL: Issues, https://github.com/yuzhi-jiang/memos-mcp/issues
Author: Yuzhi Jiang
Classifier: License :: OSI Approved :: MIT License
Classifier: Operating System :: OS Independent
Classifier: Programming Language :: Python :: 3
Requires-Python: >=3.10
Requires-Dist: fastapi
Requires-Dist: mcp[cli]
Requires-Dist: python-dotenv
Requires-Dist: requests
Requires-Dist: starlette
Requires-Dist: uvicorn
